{
    "version": "12.75",
    "description": "Fast and powerful lossless audio compressor",
    "homepage": "https://monkeysaudio.com",
    "license": "Freeware",
    "architecture": {
        "32bit": {
            "url": "https://monkeysaudio.com/files/MAC_1275.exe#/dl.7z",
            "hash": "68e7dedfd6efacc6affe5bc753d16373f546a86a412d65fc3235600ecd186a03"
        },
        "64bit": {
            "url": "https://monkeysaudio.com/files/MAC_1275_x64.exe#/dl.7z",
            "hash": "0dd101358ba15075aa3bf8e7c4f111c874857b15518c48b4a938c7e6c4a96e51"
        }
    },
    "pre_install": "Remove-Item \"$dir\\`$PLUGINSDIR\", \"$dir\\`$SYSDIR\", \"$dir\\uninstall.exe.nsis\", \"$dir\\Uninstaller.exe\" -Force -Recurse",
    "bin": "MAC.exe",
    "checkver": {
        "url": "https://monkeysaudio.com/download.html",
        "regex": "\\s+<h2>Monkey's Audio ([\\d.]+)</h2>"
    },
    "autoupdate": {
        "architecture": {
            "32bit": {
                "url": "https://monkeysaudio.com/files/MAC_$cleanVersion.exe#/dl.7z"
            },
            "64bit": {
                "url": "https://monkeysaudio.com/files/MAC_$cleanVersion_x64.exe#/dl.7z"
            }
        }
    }
}
