{
    "version": "10.50",
    "description": "Fast and powerful lossless audio compressor",
    "homepage": "https://monkeysaudio.com",
    "license": "Freeware",
    "architecture": {
        "32bit": {
            "url": "https://monkeysaudio.com/files/MAC_1050.exe#/dl.7z",
            "hash": "08cee8aeccdc2bddcca15cc9be864fd476b835eb9c2d7326067f26d9282ef66d"
        },
        "64bit": {
            "url": "https://monkeysaudio.com/files/MAC_1050_x64.exe#/dl.7z",
            "hash": "25e380b9d78a1b21ef2b0b5b8117b7078fe904cd79dc1014678eac107cfe496a"
        }
    },
    "pre_install": "Remove-Item \"$dir\\`$PLUGINSDIR\", \"$dir\\`$SYSDIR\", \"$dir\\uninstall.exe.nsis\", \"$dir\\Uninstaller.exe\" -Force -Recurse",
    "bin": "MAC.exe",
    "checkver": {
        "url": "https://monkeysaudio.com/download.html",
        "regex": "\\s+<h2>Monkey's Audio ([\\d.]+)</h2>"
    },
    "autoupdate": {
        "architecture": {
            "32bit": {
                "url": "https://monkeysaudio.com/files/MAC_$cleanVersion.exe#/dl.7z"
            },
            "64bit": {
                "url": "https://monkeysaudio.com/files/MAC_$cleanVersion_x64.exe#/dl.7z"
            }
        }
    }
}
