{
    "version": "11.64",
    "description": "Fast and powerful lossless audio compressor",
    "homepage": "https://monkeysaudio.com",
    "license": "Freeware",
    "architecture": {
        "32bit": {
            "url": "https://monkeysaudio.com/files/MAC_1164.exe#/dl.7z",
            "hash": "6b5ce1098f11e2b23d75ec5b74c387b73c78554795303084978bdfdeaa942103"
        },
        "64bit": {
            "url": "https://monkeysaudio.com/files/MAC_1164_x64.exe#/dl.7z",
            "hash": "07b30a82ca98c3a12b04c372ee016b1e0b188fa4f70aa3b34236348af0cf4272"
        }
    },
    "pre_install": "Remove-Item \"$dir\\`$PLUGINSDIR\", \"$dir\\`$SYSDIR\", \"$dir\\uninstall.exe.nsis\", \"$dir\\Uninstaller.exe\" -Force -Recurse",
    "bin": "MAC.exe",
    "checkver": {
        "url": "https://monkeysaudio.com/download.html",
        "regex": "\\s+<h2>Monkey's Audio ([\\d.]+)</h2>"
    },
    "autoupdate": {
        "architecture": {
            "32bit": {
                "url": "https://monkeysaudio.com/files/MAC_$cleanVersion.exe#/dl.7z"
            },
            "64bit": {
                "url": "https://monkeysaudio.com/files/MAC_$cleanVersion_x64.exe#/dl.7z"
            }
        }
    }
}
