{
    "version": "2.1.22.1289",
    "description": "A Simple ACME Client",
    "homepage": "https://www.win-acme.com",
    "license": "Apache-2.0",
    "architecture": {
        "64bit": {
            "url": [
                "https://github.com/win-acme/win-acme/releases/download/v2.1.22.1289/win-acme.v2.1.22.1289.x64.pluggable.zip",
                "https://github.com/win-acme/win-acme/releases/download/v2.1.22.1289/plugin.validation.dns.route53.v2.1.22.1289.zip"
            ],
            "hash": [
                "f6d1eaf7eedfcef319ef09960a0784b35491fce6a412091e6f63a3f77be2a4de",
                "d5214021d086388b77343ae8e65bf180fe2acf50e086063ca1f94a856a1a207f"
            ]
        },
        "32bit": {
            "url": [
                "https://github.com/win-acme/win-acme/releases/download/v2.1.22.1289/win-acme.v2.1.22.1289.x86.pluggable.zip",
                "https://github.com/win-acme/win-acme/releases/download/v2.1.22.1289/plugin.validation.dns.route53.v2.1.22.1289.zip"
            ],
            "hash": [
                "c13081a7545c4fe53ef1d70aa4f45dd50659e7766a005e68b02dd51ab125e391",
                "d5214021d086388b77343ae8e65bf180fe2acf50e086063ca1f94a856a1a207f"
            ]
        }
    },
    "pre_install": "if (!(Test-Path \"$persist_dir\\settings.json\")) { Copy-Item \"$dir\\settings_default.json\" \"$dir\\settings.json\" }",
    "bin": "wacs.exe",
    "persist": "settings.json",
    "checkver": "/releases/download/v([\\d.]+)/win-acme.v(?<build>[\\d.]+).x64",
    "autoupdate": {
        "architecture": {
            "64bit": {
                "url": [
                    "https://github.com/win-acme/win-acme/releases/download/v$version/win-acme.v$matchBuild.x64.pluggable.zip",
                    "https://github.com/win-acme/win-acme/releases/download/v$version/plugin.validation.dns.route53.v$matchBuild.zip"
                ]
            },
            "32bit": {
                "url": [
                    "https://github.com/win-acme/win-acme/releases/download/v$version/win-acme.v$matchBuild.x86.pluggable.zip",
                    "https://github.com/win-acme/win-acme/releases/download/v$version/plugin.validation.dns.route53.v$matchBuild.zip"
                ]
            }
        }
    }
}
